sbcluster/__init__.py
sbcluster/_cluster.py
sbcluster/_defs.py
sbcluster/py.typed
sbcluster-0.3.6.dist-info/licenses/LICENSE
sbcluster-0.3.6.dist-info/METADATA
sbcluster-0.3.6.dist-info/WHEEL
sbcluster-0.3.6.dist-info/top_level.txt
sbcluster-0.3.6.dist-info/RECORD
